django_modular_user/__init__.py
django_modular_user/admin.py
django_modular_user/fields.py
django_modular_user/user.py
django_modular_user/user_active.py
django_modular_user/user_address.py
django_modular_user/user_base.py
django_modular_user/user_birthdate.py
django_modular_user/user_email.py
django_modular_user/user_joined.py
django_modular_user/user_lastlogin.py
django_modular_user/user_name_full.py
django_modular_user/user_name_parts.py
django_modular_user/user_password.py
django_modular_user/user_permissions.py
django_modular_user/user_phone_number.py
django_modular_user/user_staff.py
django_modular_user/user_username.py
django_modular_user-0.2.1.dist-info/LICENSE
django_modular_user-0.2.1.dist-info/METADATA
django_modular_user-0.2.1.dist-info/WHEEL
django_modular_user-0.2.1.dist-info/top_level.txt
django_modular_user-0.2.1.dist-info/zip-safe
django_modular_user-0.2.1.dist-info/RECORD
