Metadata-Version: 2.1
Name: django-modular-user
Version: 0.2.1
Summary: Modular user model for Django
Home-page: https://gitlab.com/aiakos/django-modular-user
Author: Aiakos Contributors
Author-email: aiakos@aiakosauth.com
License: UNKNOWN
Keywords: django user model auth email phone number
Platform: UNKNOWN
Classifier: Development Status :: 4 - Beta
Classifier: Intended Audience :: Developers
Classifier: Intended Audience :: System Administrators
Classifier: Topic :: System :: Systems Administration :: Authentication/Directory
Classifier: License :: OSI Approved :: MIT License
Classifier: Programming Language :: Python
Classifier: Programming Language :: Python :: 3
Classifier: Programming Language :: Python :: 3 :: Only
Classifier: Programming Language :: Python :: 3.6
Classifier: Programming Language :: Python :: 3.7
Classifier: Framework :: Django
Classifier: Framework :: Django :: 2.0
Classifier: Framework :: Django :: 2.1
Requires-Dist: django (<2.99,>=2.0.0)
